mcsrvstats/__init__.py
mcsrvstats/main.py
mcsrvstats-0.1.2.dist-info/LICENSE
mcsrvstats-0.1.2.dist-info/METADATA
mcsrvstats-0.1.2.dist-info/WHEEL
mcsrvstats-0.1.2.dist-info/top_level.txt
mcsrvstats-0.1.2.dist-info/RECORD
